[
    {
        "id": "a9744a6d3cbf46cf",
        "type": "tab",
        "label": "Flow 1",
        "disabled": false,
        "info": "",
        "env": []
    },
    {
        "id": "8ef736210366c74b",
        "type": "http in",
        "z": "a9744a6d3cbf46cf",
        "name": "",
        "url": "/speed",
        "method": "get",
        "upload": false,
        "swaggerDoc": "",
        "x": 230,
        "y": 200,
        "wires": [
            [
                "d3aee49cc6378f5e"
            ]
        ]
    },
    {
        "id": "84380587cf21d276",
        "type": "http in",
        "z": "a9744a6d3cbf46cf",
        "name": "",
        "url": "/load",
        "method": "get",
        "upload": false,
        "swaggerDoc": "",
        "x": 220,
        "y": 260,
        "wires": [
            [
                "7dddf88cc1c4d0ea"
            ]
        ]
    },
    {
        "id": "d3aee49cc6378f5e",
        "type": "function",
        "z": "a9744a6d3cbf46cf",
        "name": "function 1",
        "func": "msg.payload = Math.random();\nreturn msg;",
        "outputs": 1,
        "timeout": 0,
        "noerr": 0,
        "initialize": "",
        "finalize": "",
        "libs": [],
        "x": 400,
        "y": 200,
        "wires": [
            [
                "eb3d6ca40c9a936c"
            ]
        ]
    },
    {
        "id": "7dddf88cc1c4d0ea",
        "type": "function",
        "z": "a9744a6d3cbf46cf",
        "name": "function 2",
        "func": "msg.payload = Math.random();\nreturn msg;",
        "outputs": 1,
        "timeout": 0,
        "noerr": 0,
        "initialize": "",
        "finalize": "",
        "libs": [],
        "x": 400,
        "y": 260,
        "wires": [
            [
                "65df729074a7b057"
            ]
        ]
    },
    {
        "id": "eb3d6ca40c9a936c",
        "type": "http response",
        "z": "a9744a6d3cbf46cf",
        "name": "",
        "statusCode": "200",
        "headers": {
            "content-type": "application/json"
        },
        "x": 640,
        "y": 200,
        "wires": []
    },
    {
        "id": "65df729074a7b057",
        "type": "http response",
        "z": "a9744a6d3cbf46cf",
        "name": "",
        "statusCode": "200",
        "headers": {
            "content-type": "application/json"
        },
        "x": 600,
        "y": 260,
        "wires": []
    }
]